pymedphys_sphinxtheme/__init__.py
pymedphys_sphinxtheme/_install_requires.py
pymedphys_sphinxtheme/_version.py
pymedphys_sphinxtheme/breadcrumbs.html
pymedphys_sphinxtheme/footer.html
pymedphys_sphinxtheme/layout.html
pymedphys_sphinxtheme/search.html
pymedphys_sphinxtheme/searchbox.html
pymedphys_sphinxtheme/theme.conf
pymedphys_sphinxtheme/versions.html
pymedphys_sphinxtheme/static/.gitignore
pymedphys_sphinxtheme/static/android-chrome-192x192.png
pymedphys_sphinxtheme/static/android-chrome-512x512.png
pymedphys_sphinxtheme/static/apple-touch-icon.png
pymedphys_sphinxtheme/static/browserconfig.xml
pymedphys_sphinxtheme/static/favicon-16x16.png
pymedphys_sphinxtheme/static/favicon-32x32.png
pymedphys_sphinxtheme/static/favicon.ico
pymedphys_sphinxtheme/static/mstile-150x150.png
pymedphys_sphinxtheme/static/safari-pinned-tab.svg
pymedphys_sphinxtheme/static/site.webmanifest
pymedphys_sphinxtheme/static/css/theme.css
pymedphys_sphinxtheme/static/fonts/Roboto-Slab-Bold.woff
pymedphys_sphinxtheme/static/fonts/Roboto-Slab-Bold.woff2
pymedphys_sphinxtheme/static/fonts/Roboto-Slab-Light.woff
pymedphys_sphinxtheme/static/fonts/Roboto-Slab-Light.woff2
pymedphys_sphinxtheme/static/fonts/Roboto-Slab-Regular.woff
pymedphys_sphinxtheme/static/fonts/Roboto-Slab-Regular.woff2
pymedphys_sphinxtheme/static/fonts/Roboto-Slab-Thin.woff
pymedphys_sphinxtheme/static/fonts/Roboto-Slab-Thin.woff2
pymedphys_sphinxtheme/static/fonts/fontawesome-webfont.eot
pymedphys_sphinxtheme/static/fonts/fontawesome-webfont.svg
pymedphys_sphinxtheme/static/fonts/fontawesome-webfont.ttf
pymedphys_sphinxtheme/static/fonts/fontawesome-webfont.woff
pymedphys_sphinxtheme/static/fonts/fontawesome-webfont.woff2
pymedphys_sphinxtheme/static/fonts/lato-bold-italic.woff
pymedphys_sphinxtheme/static/fonts/lato-bold-italic.woff2
pymedphys_sphinxtheme/static/fonts/lato-bold.woff
pymedphys_sphinxtheme/static/fonts/lato-bold.woff2
pymedphys_sphinxtheme/static/fonts/lato-normal-italic.woff
pymedphys_sphinxtheme-0.11.0.dist-info/LICENSE
pymedphys_sphinxtheme-0.11.0.dist-info/METADATA
pymedphys_sphinxtheme-0.11.0.dist-info/WHEEL
pymedphys_sphinxtheme-0.11.0.dist-info/entry_points.txt
pymedphys_sphinxtheme-0.11.0.dist-info/top_level.txt
pymedphys_sphinxtheme-0.11.0.dist-info/RECORD
